dctap/.gitignore
dctap/__init__.py
dctap/cli.py
dctap/config.py
dctap/csvreader.py
dctap/defaults.py
dctap/exceptions.py
dctap/inspect.py
dctap/loggers.py
dctap/tapclasses.py
dctap/utils.py
dctap-0.4.5.dist-info/entry_points.txt
dctap-0.4.5.dist-info/LICENSE
dctap-0.4.5.dist-info/WHEEL
dctap-0.4.5.dist-info/METADATA
dctap-0.4.5.dist-info/RECORD
