Metadata-Version: 2.1
Name: dctap
Version: 0.4.5
Summary: Convert a Tabular Application Profile from CSV into JSON.
Home-page: https://github.com/dcmi/dctap-python
Author: DCMI
Author-email: tom@tombaker.org
Requires-Python: >=3.7
Classifier: Development Status :: 3 - Alpha
Classifier: Programming Language :: Python :: 3.7
Classifier: Programming Language :: Python :: 3.8
Classifier: Programming Language :: Python :: 3.9
Classifier: Programming Language :: Python :: 3.10
Classifier: Programming Language :: Python :: 3.11
Requires-Dist: click
Requires-Dist: ruamel.base
Requires-Dist: ruamel.yaml
Requires-Dist: sphinx ; extra == "doc"
Requires-Dist: sphinx_rtd_theme ; extra == "doc"
Requires-Dist: black ; extra == "test"
Requires-Dist: coverage ; extra == "test"
Requires-Dist: ipdb ; extra == "test"
Requires-Dist: ipykernel ; extra == "test"
Requires-Dist: ipython ; extra == "test"
Requires-Dist: pylint ; extra == "test"
Requires-Dist: pytest ; extra == "test"
Requires-Dist: pytest-cov ; extra == "test"
Provides-Extra: doc
Provides-Extra: test
